src/__init__.py
src/tommath/__init__.py
src/tommath/cacu.py
tomlibrary-3.0.6.dist-info/METADATA
tomlibrary-3.0.6.dist-info/WHEEL
tomlibrary-3.0.6.dist-info/top_level.txt
tomlibrary-3.0.6.dist-info/RECORD
