Metadata-Version: 2.1
Name: tomlibrary
Version: 3.0.6
Summary: schooldevops sample lib
Home-page: https://github.com/schooldevops/python-tutorials
Author: Schooldevops
Author-email: schooldevops@gmail.com
Project-URL: Bug Tracker, https://github.com/schooldevops/python-tutorials/issues
Classifier: Programming Language :: Python :: 3
Classifier: License :: OSI Approved :: MIT License
Classifier: Operating System :: OS Independent
Requires-Python: >=3.6
